cyberdesk/__init__.py
cyberdesk/client.py
cyberdesk/types.py
cyberdesk-2.2.21.dist-info/licenses/LICENSE
openapi_client/cyberdesk_cloud_client/__init__.py
openapi_client/cyberdesk_cloud_client/client.py
openapi_client/cyberdesk_cloud_client/errors.py
openapi_client/cyberdesk_cloud_client/py.typed
openapi_client/cyberdesk_cloud_client/types.py
openapi_client/cyberdesk_cloud_client/api/__init__.py
openapi_client/cyberdesk_cloud_client/api/computer/__init__.py
openapi_client/cyberdesk_cloud_client/api/computer/copy_to_clipboard_v1_computer_machine_id_copy_to_clipboard_post.py
openapi_client/cyberdesk_cloud_client/api/computer/fs_list_v1_computer_machine_id_fs_list_get.py
openapi_client/cyberdesk_cloud_client/api/computer/fs_read_v1_computer_machine_id_fs_read_get.py
openapi_client/cyberdesk_cloud_client/api/computer/fs_write_v1_computer_machine_id_fs_write_post.py
openapi_client/cyberdesk_cloud_client/api/computer/get_display_dimensions_v1_computer_machine_id_display_dimensions_get.py
openapi_client/cyberdesk_cloud_client/api/computer/get_mouse_position_v1_computer_machine_id_input_mouse_position_get.py
openapi_client/cyberdesk_cloud_client/api/computer/get_screenshot_v1_computer_machine_id_display_screenshot_get.py
openapi_client/cyberdesk_cloud_client/api/computer/keyboard_key_v1_computer_machine_id_input_keyboard_key_post.py
openapi_client/cyberdesk_cloud_client/api/computer/keyboard_type_v1_computer_machine_id_input_keyboard_type_post.py
openapi_client/cyberdesk_cloud_client/api/computer/mouse_click_v1_computer_machine_id_input_mouse_click_post.py
openapi_client/cyberdesk_cloud_client/api/computer/mouse_drag_v1_computer_machine_id_input_mouse_drag_post.py
openapi_client/cyberdesk_cloud_client/api/computer/mouse_move_v1_computer_machine_id_input_mouse_move_post.py
openapi_client/cyberdesk_cloud_client/api/computer/mouse_scroll_v1_computer_machine_id_input_mouse_scroll_post.py
openapi_client/cyberdesk_cloud_client/api/computer/powershell_exec_v1_computer_machine_id_shell_powershell_exec_post.py
cyberdesk-2.2.21.dist-info/METADATA
cyberdesk-2.2.21.dist-info/WHEEL
cyberdesk-2.2.21.dist-info/top_level.txt
cyberdesk-2.2.21.dist-info/RECORD
