Metadata-Version: 2.4
Name: cyberdesk
Version: 2.2.21
Summary: The official Python SDK for Cyberdesk
Author-email: Cyberdesk Team <dev@cyberdesk.io>
License-Expression: MIT
License-File: LICENSE
Requires-Dist: httpx
Requires-Dist: attrs
Provides-Extra: dev
Requires-Dist: openapi-python-client; extra == "dev"
Requires-Dist: build; extra == "dev"
Requires-Dist: twine; extra == "dev"
Provides-Extra: testing
Requires-Dist: svix>=1.0.0; extra == "testing"
Requires-Dist: fastapi>=0.100.0; extra == "testing"
Requires-Dist: uvicorn[standard]>=0.30.0; extra == "testing"
Requires-Dist: python-dotenv>=1.0.0; extra == "testing"
Requires-Dist: pytest>=8.0.0; extra == "testing"
Requires-Dist: pytest-asyncio>=0.23.0; extra == "testing"
Provides-Extra: all
Requires-Dist: openapi-python-client; extra == "all"
Requires-Dist: build; extra == "all"
Requires-Dist: twine; extra == "all"
Requires-Dist: svix>=1.0.0; extra == "all"
Requires-Dist: fastapi>=0.100.0; extra == "all"
Requires-Dist: uvicorn[standard]>=0.30.0; extra == "all"
Requires-Dist: python-dotenv>=1.0.0; extra == "all"
Requires-Dist: pytest>=8.0.0; extra == "all"
Requires-Dist: pytest-asyncio>=0.23.0; extra == "all"
Dynamic: license-file
